Workbook

Sheet Executive Summary
A1: Example Office Building
A2: Investment Summary | prepared with the automated underwriting tool
A4: THE DEAL
B5: Purchase Price | C5: =Assumptions!$C$5 -> 20000000
B6: Year 1 NOI | C6: =Assumptions!$C$6 -> 1200000
B7: Going-In Cap Rate | C7: =Assumptions!$C$7 -> 0.06
B8: Hold Period | C8: =Assumptions!$C$11 -> 5
B9: Exit Cap Rate | C9: =Assumptions!$C$12 -> 0.0625
A11: RETURNS
B12: Unlevered IRR | C12: ='Cash Flow Model'!C20 -> 0.078909292 | E12: HEADLINE RETURN
B13: Unlevered Equity Multiple | C13: ='Cash Flow Model'!C21 -> 1.4091932 | E13: ='Cash Flow Model'!C22 -> 0.11057465
B14: Levered IRR | C14: ='Cash Flow Model'!C22 -> 0.11057465 | E14: Levered IRR, 5-year hold
B15: Levered Equity Multiple | C15: ='Cash Flow Model'!C23 -> 1.6250638
B16: Year 1 DSCR | C16: ='Cash Flow Model'!D16 -> 1.4676814
A18: CAPITAL STRUCTURE
B19: Loan Amount | C19: =Assumptions!$C$20 -> 12000000
B20: Equity Required | C20: =Assumptions!$C$21 -> 8000000
B21: Annual Debt Service | C21: =Assumptions!$C$22 -> 817616.16
A23: BASIS & LIMITATIONS
B24: - NOI grows at a single constant rate; no explicit lease-up, rollover, or capex schedule.
B25: - Terminal value is a forward-NOI capitalization, net of selling costs.
B26: - Debt is fixed-rate and fully amortizing; no interest-only period or refinancing.
B27: - No tax treatment, partnership waterfall, or promote structure.
B28: - Screening-level analysis. A deal clearing this screen still requires a full property-level model.

Sheet Assumptions
A1: Example Office Building
A2: Underwriting assumptions | blue cells are inputs - edit these
A4: PROPERTY & PRICING
B5: Purchase Price | C5: 20000000 | D5: Contract / ask price
B6: Year 1 Net Operating Income | C6: 1200000 | D6: In-place NOI from rent roll
B7: Going-In Cap Rate | C7: =C6/C5 -> 0.06 | D7: Calculated: Year 1 NOI / Purchase Price
A9: GROWTH & EXIT
B10: Annual NOI Growth | C10: 0.03 | D10: Applied to NOI each year
B11: Hold Period (Years) | C11: 5 | D11: Years to disposition
B12: Exit Cap Rate | C12: 0.0625 | D12: Applied to forward (Year N+1) NOI
B13: Selling Costs | C13: 0.02 | D13: Broker fees + closing costs at sale
A15: CAPITAL STRUCTURE
B16: Loan to Value (LTV) | C16: 0.6 | D16: Set to 0% for an all-cash deal
B17: Interest Rate | C17: 0.055 | D17: Fixed rate
B18: Amortization (Years) | C18: 30 | D18: Fully amortizing
B20: Loan Amount | C20: =C5*C16 -> 12000000
B21: Equity Required | C21: =C5-C20 -> 8000000
B22: Annual Debt Service | C22: =IF(C20=0,0,C20*((C17/12)*(1+C17/12)^(C18*12))/((1+C17/12)^(C18*12)-1)*12) -> 817616.16 | D22: Standard amortizing payment, annualized

Sheet Cash Flow Model
A1: Example Office Building - Cash Flow Model
A2: All figures calculated live from the Assumptions tab
C4: At Close | D4: Year 1 | E4: Year 2 | F4: Year 3 | G4: Year 4 | H4: Year 5
B6: Net Operating Income | D6: =Assumptions!$C$6 -> 1200000 | E6: =D6*(1+Assumptions!$C$10) -> 1236000 | F6: =E6*(1+Assumptions!$C$10) -> 1273080 | G6: =F6*(1+Assumptions!$C$10) -> 1311272.4 | H6: =G6*(1+Assumptions!$C$10) -> 1350610.6
B7: Net Sale Proceeds | H7: =(H6*(1+Assumptions!$C$10))/Assumptions!$C$12*(1-Assumptions!$C$13) -> 21812901
B9: UNLEVERED CASH FLOW | C9: =-Assumptions!$C$5 -> -20000000 | D9: =D6 -> 1200000 | E9: =E6 -> 1236000 | F9: =F6 -> 1273080 | G9: =G6 -> 1311272.4 | H9: =H6+H7 -> 23163512
B11: Debt Service | D11: =-Assumptions!$C$22 -> -817616.16 | E11: =-Assumptions!$C$22 -> -817616.16 | F11: =-Assumptions!$C$22 -> -817616.16 | G11: =-Assumptions!$C$22 -> -817616.16 | H11: =-Assumptions!$C$22 -> -817616.16
B12: Loan Balance Repaid at Exit | H12: =-(Assumptions!$C$20*(1+Assumptions!$C$17/12)^(Assumptions!$C$11*12)-Assumptions!$C$22/12/(Assumptions!$C$17/12)*((1+Assumptions!$C$17/12)^(Assumptions!$C$11*12)-1)) -> -11095272
B14: LEVERED CASH FLOW | C14: =-Assumptions!$C$21 -> -8000000 | D14: =D9+D11 -> 382383.84 | E14: =E9+E11 -> 418383.84 | F14: =F9+F11 -> 455463.84 | G14: =G9+G11 -> 493656.24 | H14: =H9+H11+H12 -> 11250623
B16: Debt Service Coverage Ratio | D16: =D6/Assumptions!$C$22 -> 1.4676814 | E16: =E6/Assumptions!$C$22 -> 1.5117118 | F16: =F6/Assumptions!$C$22 -> 1.5570632 | G16: =G6/Assumptions!$C$22 -> 1.603775 | H16: =H6/Assumptions!$C$22 -> 1.6518883
A19: RETURNS
B20: Unlevered IRR | C20: =IRR(C9:H9) -> 0.078909292
B21: Unlevered Equity Multiple | C21: =SUM(D9:H9)/-C9 -> 1.4091932
B22: Levered IRR | C22: =IRR(C14:H14) -> 0.11057465
B23: Levered Equity Multiple | C23: =SUM(D14:H14)/-C14 -> 1.6250638

Sheet Sensitivity
A1: Levered IRR Sensitivity
A2: Purchase price (rows) vs. exit cap rate (columns)
B4: Price / Exit Cap | C4: 5.50% | D4: 5.88% | E4: 6.25% | F4: 6.62% | G4: 7.00%
B5: 95.0% of ask | C5: 0.18487628 | D5: 0.16075226 | E5: 0.13763356 | F5: 0.11533917 | G5: 0.093712555
B6: 97.5% of ask | C6: 0.17196814 | D6: 0.14750041 | E6: 0.12400252 | F6: 0.10128974 | G6: 0.079200845
B7: 100.0% of ask | C7: 0.15930004 | D7: 0.13447178 | E7: 0.11057465 | F7: 0.087419415 | G7: 0.064839132
B8: 102.5% of ask | C8: 0.14685127 | D8: 0.12164464 | E8: 0.097326851 | F8: 0.073703204 | G8: 0.050599832
B9: 105.0% of ask | C9: 0.13460242 | D9: 0.10899853 | E9: 0.084237138 | F9: 0.060117008 | G9: 0.036455899
B11: Base case is the center cell. Green indicates higher returns.

Sheet Deal Screen
A1: Deal Screen
A2: All deals underwritten on identical assumptions, ranked by IRR
B4: Deal | C4: Purchase Price | D4: Going-In Cap | E4: Exit Cap | F4: Unlevered IRR | G4: Levered IRR | H4: Equity Multiple | I4: Yr1 DSCR
B5: Desert Commons | C5: 14500000 | D5: 0.065 | E5: 0.065 | F5: 0.089350394 | G5: 0.14321347 | H5: 1.8468186 | I5: 1.4676814
B6: 3990 Ruffin Place | C6: 31000000 | D6: 0.063 | E6: 0.06 | F6: 0.098517342 | G6: 0.13977229 | H6: 2.2615643 | I6: 1.6811623
B7: Example Office Building | C7: 20000000 | D7: 0.06 | E7: 0.0625 | F7: 0.078909292 | G7: 0.11057465 | H7: 1.6250638 | I7: 1.4676814
B9: Top-ranked deal highlighted. Ranking is quantitative only.

Sheet Investment Memo
A1: Investment Memorandum
A2: Example Office Building
B4: INVESTMENT MEMORANDUM
B5: Example Office Building
B7: RECOMMENDATION SUMMARY
B8: Proposed acquisition of Example Office Building at $20,000,000, a 6.00% going-in capitalization rate on Year 1 net operating income of $1,200,000. Base-case underwriting projects a 11.06% levered internal rate of return and a 1.63x equity multiple over a 5-year hold.
B10: UNDERWRITING ASSUMPTIONS
B11: Net operating income is grown at 3.00% annually. Disposition is underwritten at a 6.25% exit capitalization rate applied to forward NOI, net of 2.0% selling costs, producing a terminal value of $21,812,901. The capital structure assumes 60% loan-to-value at 5.50% interest on a 30-year amortization schedule, requiring $8,000,000 of equity against a $12,000,000 loan. Year 1 debt service coverage is 1.47x.
B13: KEY RISKS
B14: Returns are most sensitive to exit capitalization rate and achieved disposition pricing; refer to the attached sensitivity analysis for IRR outcomes across the pricing and exit-cap range. Principal risks include underperformance against the NOI growth assumption, cap rate expansion at exit, and interest rate exposure at refinancing.
B16: NEXT STEPS
B17: Quantitative base case is complete. Qualitative diligence — market comparables, tenant credit and rollover schedule, physical condition assessment, and submarket supply pipeline — remains outstanding prior to a final recommendation.
